gh_reader/__init__.py
gh_reader/download.py
gh_reader/export.py
gh_reader/gh_api.py
gh_reader/misc.py
gh_reader/extractors/__init__.py
gh_reader/extractors/commits.py
gh_reader/extractors/issue_comments.py
gh_reader/extractors/issue_events.py
gh_reader/extractors/issue_labels.py
gh_reader/extractors/issues.py
gh_reader/extractors/issues_pr.py
gh_reader/extractors/labels.py
gh_reader/extractors/pull_requests.py
gh_reader/extractors/reactions.py
gh_reader/extractors/repository.py
gh_reader/extractors/stargazers.py
gh_reader/extractors/users.py
gh_reader/schemas/commits.yml
gh_reader/schemas/issue_comments.yml
gh_reader/schemas/issue_labels.yml
gh_reader/schemas/issues.yml
gh_reader/schemas/issues_pr.yml
gh_reader/schemas/labels.yml
gh_reader/schemas/pull_requests.yml
gh_reader/schemas/reactions.yml
gh_reader/schemas/repository.yml
gh_reader/schemas/stargazers.yml
gh_reader/schemas/users.yml
gh_reader/tests/test_basic.py
gh_reader-0.0.4.dist-info/METADATA
gh_reader-0.0.4.dist-info/WHEEL
gh_reader-0.0.4.dist-info/top_level.txt
gh_reader-0.0.4.dist-info/RECORD
