Metadata-Version: 2.4
Name: gh-reader
Version: 0.0.4
Summary: Extract github data into very reasonable tables.
Author-email: Michael Chow <mc_al_github@fastmail.com>
Project-URL: Homepage, https://github.com/machow/gh_reader
Keywords: template,packaging
Classifier: Programming Language :: Python :: 3.9
Classifier: Programming Language :: Python :: 3.10
Requires-Python: >=3.9
Requires-Dist: jq
Requires-Dist: requests
Requires-Dist: importlib-resources
Requires-Dist: pyarrow
Requires-Dist: pyyaml
Provides-Extra: dev
Requires-Dist: pytest; extra == "dev"
Requires-Dist: pytest-dotenv; extra == "dev"
